{
  "info": {
    "name": "SaaS Booking System API CRUD",
    "schema": "https://schema.getpostman.com/json/collection/v2.1.0/collection.json"
  },
  "item": [
    {
      "name": "User",
      "item": [
        {
          "name": "Get All Users",
          "request": { "method": "GET", "url": { "raw": "http://localhost:5000/api/users", "protocol": "http", "host": ["localhost"], "port": "5000", "path": ["api", "users"] } }
        },
        {
          "name": "Get User By ID",
          "request": { "method": "GET", "url": { "raw": "http://localhost:5000/api/users/1", "protocol": "http", "host": ["localhost"], "port": "5000", "path": ["api", "users", "1"] } }
        },
        {
          "name": "Create User",
          "request": {
            "method": "POST",
            "header": [{ "key": "Content-Type", "value": "application/json" }],
            "url": { "raw": "http://localhost:5000/api/users", "protocol": "http", "host": ["localhost"], "port": "5000", "path": ["api", "users"] },
            "body": { "mode": "raw", "raw": "{\n  \"Fullname\": \"Test User\",\n  \"Email\": \"test@example.com\",\n  \"PhoneNumber\": \"08123456789\",\n  \"Address\": \"Jl. Test\",\n  \"Password\": \"password\",\n  \"RoleId\": 1\n}" }
          }
        },
        {
          "name": "Update User",
          "request": {
            "method": "PUT",
            "header": [{ "key": "Content-Type", "value": "application/json" }],
            "url": { "raw": "http://localhost:5000/api/users/1", "protocol": "http", "host": ["localhost"], "port": "5000", "path": ["api", "users", "1"] },
            "body": { "mode": "raw", "raw": "{\n  \"Fullname\": \"Updated User\"\n}" }
          }
        },
        {
          "name": "Delete User",
          "request": { "method": "DELETE", "url": { "raw": "http://localhost:5000/api/users/1", "protocol": "http", "host": ["localhost"], "port": "5000", "path": ["api", "users", "1"] } }
        }
      ]
    },
    {
      "name": "Role",
      "item": [
        {
          "name": "Get All Roles",
          "request": { "method": "GET", "url": { "raw": "http://localhost:5000/api/roles", "protocol": "http", "host": ["localhost"], "port": "5000", "path": ["api", "roles"] } }
        },
        {
          "name": "Get Role By ID",
          "request": { "method": "GET", "url": { "raw": "http://localhost:5000/api/roles/1", "protocol": "http", "host": ["localhost"], "port": "5000", "path": ["api", "roles", "1"] } }
        },
        {
          "name": "Create Role",
          "request": {
            "method": "POST",
            "header": [{ "key": "Content-Type", "value": "application/json" }],
            "url": { "raw": "http://localhost:5000/api/roles", "protocol": "http", "host": ["localhost"], "port": "5000", "path": ["api", "roles"] },
            "body": { "mode": "raw", "raw": "{\n  \"Name\": \"Admin\"\n}" }
          }
        },
        {
          "name": "Update Role",
          "request": {
            "method": "PUT",
            "header": [{ "key": "Content-Type", "value": "application/json" }],
            "url": { "raw": "http://localhost:5000/api/roles/1", "protocol": "http", "host": ["localhost"], "port": "5000", "path": ["api", "roles", "1"] },
            "body": { "mode": "raw", "raw": "{\n  \"Name\": \"User\"\n}" }
          }
        },
        {
          "name": "Delete Role",
          "request": { "method": "DELETE", "url": { "raw": "http://localhost:5000/api/roles/1", "protocol": "http", "host": ["localhost"], "port": "5000", "path": ["api", "roles", "1"] } }
        }
      ]
    },
    {
      "name": "Resource",
      "item": [
        {
          "name": "Get All Resources",
          "request": { "method": "GET", "url": { "raw": "http://localhost:5000/api/resources", "protocol": "http", "host": ["localhost"], "port": "5000", "path": ["api", "resources"] } }
        },
        {
          "name": "Get Resource By ID",
          "request": { "method": "GET", "url": { "raw": "http://localhost:5000/api/resources/1", "protocol": "http", "host": ["localhost"], "port": "5000", "path": ["api", "resources", "1"] } }
        },
        {
          "name": "Create Resource",
          "request": {
            "method": "POST",
            "header": [{ "key": "Content-Type", "value": "application/json" }],
            "url": { "raw": "http://localhost:5000/api/resources", "protocol": "http", "host": ["localhost"], "port": "5000", "path": ["api", "resources"] },
            "body": { "mode": "raw", "raw": "{\n  \"Name\": \"Room 1\",\n  \"BookingType\": \"Room\",\n  \"ResourceType\": \"Meeting\",\n  \"Description\": \"Meeting Room\",\n  \"IsActive\": true\n}" }
          }
        },
        {
          "name": "Update Resource",
          "request": {
            "method": "PUT",
            "header": [{ "key": "Content-Type", "value": "application/json" }],
            "url": { "raw": "http://localhost:5000/api/resources/1", "protocol": "http", "host": ["localhost"], "port": "5000", "path": ["api", "resources", "1"] },
            "body": { "mode": "raw", "raw": "{\n  \"Description\": \"Updated Room\"\n}" }
          }
        },
        {
          "name": "Delete Resource",
          "request": { "method": "DELETE", "url": { "raw": "http://localhost:5000/api/resources/1", "protocol": "http", "host": ["localhost"], "port": "5000", "path": ["api", "resources", "1"] } }
        }
      ]
    },
    {
      "name": "Booking",
      "item": [
        {
          "name": "Get All Bookings",
          "request": { "method": "GET", "url": { "raw": "http://localhost:5000/api/bookings", "protocol": "http", "host": ["localhost"], "port": "5000", "path": ["api", "bookings"] } }
        },
        {
          "name": "Get Booking By ID",
          "request": { "method": "GET", "url": { "raw": "http://localhost:5000/api/bookings/1", "protocol": "http", "host": ["localhost"], "port": "5000", "path": ["api", "bookings", "1"] } }
        },
        {
          "name": "Create Booking",
          "request": {
            "method": "POST",
            "header": [{ "key": "Content-Type", "value": "application/json" }],
            "url": { "raw": "http://localhost:5000/api/bookings", "protocol": "http", "host": ["localhost"], "port": "5000", "path": ["api", "bookings"] },
            "body": { "mode": "raw", "raw": "{\n  \"UserId\": 1,\n  \"ResourceId\": 1,\n  \"StartTime\": \"2024-06-07T09:00:00Z\",\n  \"EndTime\": \"2024-06-07T10:00:00Z\",\n  \"Status\": \"Pending\",\n  \"BookingCode\": \"BK001\"\n}" }
          }
        },
        {
          "name": "Update Booking",
          "request": {
            "method": "PUT",
            "header": [{ "key": "Content-Type", "value": "application/json" }],
            "url": { "raw": "http://localhost:5000/api/bookings/1", "protocol": "http", "host": ["localhost"], "port": "5000", "path": ["api", "bookings", "1"] },
            "body": { "mode": "raw", "raw": "{\n  \"Status\": \"Confirmed\"\n}" }
          }
        },
        {
          "name": "Delete Booking",
          "request": { "method": "DELETE", "url": { "raw": "http://localhost:5000/api/bookings/1", "protocol": "http", "host": ["localhost"], "port": "5000", "path": ["api", "bookings", "1"] } }
        }
      ]
    },
    {
      "name": "RoomBookingDetail",
      "item": [
        {
          "name": "Get All RoomBookingDetails",
          "request": { "method": "GET", "url": { "raw": "http://localhost:5000/api/room-booking-details", "protocol": "http", "host": ["localhost"], "port": "5000", "path": ["api", "room-booking-details"] } }
        },
        {
          "name": "Get RoomBookingDetail By ID",
          "request": { "method": "GET", "url": { "raw": "http://localhost:5000/api/room-booking-details/1", "protocol": "http", "host": ["localhost"], "port": "5000", "path": ["api", "room-booking-details", "1"] } }
        },
        {
          "name": "Create RoomBookingDetail",
          "request": {
            "method": "POST",
            "header": [{ "key": "Content-Type", "value": "application/json" }],
            "url": { "raw": "http://localhost:5000/api/room-booking-details", "protocol": "http", "host": ["localhost"], "port": "5000", "path": ["api", "room-booking-details"] },
            "body": { "mode": "raw", "raw": "{\n  \"BookingId\": 1,\n  \"RoomDetailId\": 1,\n  \"Notes\": \"Catatan\",\n  \"ExtraInfo\": \"Info tambahan\"\n}" }
          }
        },
        {
          "name": "Update RoomBookingDetail",
          "request": {
            "method": "PUT",
            "header": [{ "key": "Content-Type", "value": "application/json" }],
            "url": { "raw": "http://localhost:5000/api/room-booking-details/1", "protocol": "http", "host": ["localhost"], "port": "5000", "path": ["api", "room-booking-details", "1"] },
            "body": { "mode": "raw", "raw": "{\n  \"Notes\": \"Update Catatan\"\n}" }
          }
        },
        {
          "name": "Delete RoomBookingDetail",
          "request": { "method": "DELETE", "url": { "raw": "http://localhost:5000/api/room-booking-details/1", "protocol": "http", "host": ["localhost"], "port": "5000", "path": ["api", "room-booking-details", "1"] } }
        }
      ]
    },
    {
      "name": "HealthBookingDetail",
      "item": [
        {
          "name": "Get All HealthBookingDetails",
          "request": { "method": "GET", "url": { "raw": "http://localhost:5000/api/health-booking-details", "protocol": "http", "host": ["localhost"], "port": "5000", "path": ["api", "health-booking-details"] } }
        },
        {
          "name": "Get HealthBookingDetail By ID",
          "request": { "method": "GET", "url": { "raw": "http://localhost:5000/api/health-booking-details/1", "protocol": "http", "host": ["localhost"], "port": "5000", "path": ["api", "health-booking-details", "1"] } }
        },
        {
          "name": "Create HealthBookingDetail",
          "request": {
            "method": "POST",
            "header": [{ "key": "Content-Type", "value": "application/json" }],
            "url": { "raw": "http://localhost:5000/api/health-booking-details", "protocol": "http", "host": ["localhost"], "port": "5000", "path": ["api", "health-booking-details"] },
            "body": { "mode": "raw", "raw": "{\n  \"UserId\": 1,\n  \"ResourceId\": 1,\n  \"StartTime\": \"2024-06-07T09:00:00Z\",\n  \"EndTime\": \"2024-06-07T10:00:00Z\",\n  \"Status\": \"Pending\",\n  \"BookingCode\": \"HB001\",\n  \"Notes\": \"Catatan\"\n}" }
          }
        },
        {
          "name": "Update HealthBookingDetail",
          "request": {
            "method": "PUT",
            "header": [{ "key": "Content-Type", "value": "application/json" }],
            "url": { "raw": "http://localhost:5000/api/health-booking-details/1", "protocol": "http", "host": ["localhost"], "port": "5000", "path": ["api", "health-booking-details", "1"] },
            "body": { "mode": "raw", "raw": "{\n  \"Status\": \"Confirmed\"\n}" }
          }
        },
        {
          "name": "Delete HealthBookingDetail",
          "request": { "method": "DELETE", "url": { "raw": "http://localhost:5000/api/health-booking-details/1", "protocol": "http", "host": ["localhost"], "port": "5000", "path": ["api", "health-booking-details", "1"] } }
        }
      ]
    },
    {
      "name": "QueueTickets",
      "item": [
        {
          "name": "Get All QueueTickets",
          "request": { "method": "GET", "url": { "raw": "http://localhost:5000/api/queue-tickets", "protocol": "http", "host": ["localhost"], "port": "5000", "path": ["api", "queue-tickets"] } }
        },
        {
          "name": "Get QueueTicket By ID",
          "request": { "method": "GET", "url": { "raw": "http://localhost:5000/api/queue-tickets/1", "protocol": "http", "host": ["localhost"], "port": "5000", "path": ["api", "queue-tickets", "1"] } }
        },
        {
          "name": "Create QueueTicket",
          "request": {
            "method": "POST",
            "header": [{ "key": "Content-Type", "value": "application/json" }],
            "url": { "raw": "http://localhost:5000/api/queue-tickets", "protocol": "http", "host": ["localhost"], "port": "5000", "path": ["api", "queue-tickets"] },
            "body": { "mode": "raw", "raw": "{\n  \"BookingId\": 1,\n  \"TicketNumber\": \"Q001\",\n  \"Status\": \"Waiting\",\n  \"CalledAt\": null,\n  \"EndAt\": null\n}" }
          }
        },
        {
          "name": "Update QueueTicket",
          "request": {
            "method": "PUT",
            "header": [{ "key": "Content-Type", "value": "application/json" }],
            "url": { "raw": "http://localhost:5000/api/queue-tickets/1", "protocol": "http", "host": ["localhost"], "port": "5000", "path": ["api", "queue-tickets", "1"] },
            "body": { "mode": "raw", "raw": "{\n  \"Status\": \"Called\"\n}" }
          }
        },
        {
          "name": "Delete QueueTicket",
          "request": { "method": "DELETE", "url": { "raw": "http://localhost:5000/api/queue-tickets/1", "protocol": "http", "host": ["localhost"], "port": "5000", "path": ["api", "queue-tickets", "1"] } }
        }
      ]
    }
  ]
}
